bloom_embedding/__init__.py
bloom_embedding/bloom.py
bloom_embedding-0.1.1.dist-info/LICENSE
bloom_embedding-0.1.1.dist-info/METADATA
bloom_embedding-0.1.1.dist-info/WHEEL
bloom_embedding-0.1.1.dist-info/top_level.txt
bloom_embedding-0.1.1.dist-info/RECORD
