Metadata-Version: 2.1
Name: bloom-embedding
Version: 0.1.1
Summary: Bloom Embedding - Pytorch
Home-page: https://github.com/i404788/bloom-embedding
Author: Ferris Kwaijtaal
Author-email: ferris+gh@devdroplets.com
License: MIT
Keywords: artificial intelligence,deep learning,transformers,attention mechanism,audio generation
Classifier: Development Status :: 4 - Beta
Classifier: Intended Audience :: Developers
Classifier: Topic :: Scientific/Engineering :: Artificial Intelligence
Classifier: License :: OSI Approved :: MIT License
Classifier: Programming Language :: Python :: 3.6
License-File: LICENSE
Requires-Dist: torch (>=1.13)
